easypsyco/__init__.py
easypsyco/__pkginfo__.py
easypsyco/easypsyco.py
tests/__init__.py
tests/test_mocks.py
easypsyco-0.3.0.dist-info/METADATA
easypsyco-0.3.0.dist-info/WHEEL
easypsyco-0.3.0.dist-info/top_level.txt
easypsyco-0.3.0.dist-info/RECORD
