Metadata-Version: 2.1
Name: easypsyco
Version: 0.3.0
Summary: A simple API on top of psycopg2
Home-page: https://github.com/scravy/easypsyco
Author: Julian Fleischer
Author-email: tirednesscankill@warhog.net
License: UNKNOWN
Platform: UNKNOWN
Classifier: Programming Language :: Python :: 3
Classifier: License :: OSI Approved :: MIT License
Classifier: Operating System :: OS Independent
Requires-Python: >=3.8
Requires-Dist: psycopg2 (==2.8.6)
